azure/iot/modelsrepository/__init__.py
azure/iot/modelsrepository/_client.py
azure/iot/modelsrepository/_constants.py
azure/iot/modelsrepository/_pseudo_parser.py
azure/iot/modelsrepository/_resolver.py
azure/iot/modelsrepository/_version.py
azure/iot/modelsrepository/dtmi_conventions.py
azure/iot/modelsrepository/exceptions.py
azure/iot/modelsrepository/py.typed
azure_iot_modelsrepository-1.0.0b2.dist-info/LICENSE
azure_iot_modelsrepository-1.0.0b2.dist-info/METADATA
azure_iot_modelsrepository-1.0.0b2.dist-info/WHEEL
azure_iot_modelsrepository-1.0.0b2.dist-info/top_level.txt
azure_iot_modelsrepository-1.0.0b2.dist-info/RECORD
